vishop/__about__.py
vishop/__init__.py
vishop/__main__.py
vishop/core.py
vishop-0.0.2.dist-info/LICENSE
vishop-0.0.2.dist-info/METADATA
vishop-0.0.2.dist-info/WHEEL
vishop-0.0.2.dist-info/entry_points.txt
vishop-0.0.2.dist-info/top_level.txt
vishop-0.0.2.dist-info/RECORD
