Metadata-Version: 2.1
Name: vishop
Version: 0.0.2
Summary: Vishop is command line VIM script publisher client.
Home-page: https://github.com/Xvezda/vishop
Author: Xvezda
Author-email: xvezda@naver.com
License: MIT
Keywords: VIM,VI,editor,plugin,package manager,utility,publishing
Platform: UNKNOWN
Classifier: Environment :: Console
Classifier: Topic :: Text Editors
Classifier: Topic :: System :: Archiving :: Packaging
Classifier: Development Status :: 4 - Beta
Classifier: License :: OSI Approved :: MIT License
Classifier: Programming Language :: Python :: 2
Classifier: Programming Language :: Python :: 2.7
Classifier: Programming Language :: Python :: 3
Classifier: Programming Language :: Python :: 3.5
Classifier: Programming Language :: Python :: 3.6
Classifier: Programming Language :: Python :: 3.7
Classifier: Programming Language :: Python :: 3.8
Requires-Dist: requests
Requires-Dist: BeautifulSoup4
